nork/__init__.py
nork/__main__.py
nork/cli/__init__.py
nork/cli/application.py
nork/commands/FrameworkNew.py
nork/commands/Install.py
nork/commands/OsEnv.py
nork/commands/__init__.py
nork/core/__init__.py
nork/core/logging.py
nork/core/paths.py
nork/framework/__init__.py
nork/framework/application.py
nork/framework/commands/Serve.py
nork/framework/commands/__init__.py
nork/framework/routing/Route.py
nork/framework/routing/Routing.py
nork/framework/routing/__init__.py
nork/framework/server/__init__.py
nork-0.1.16.dist-info/entry_points.txt
nork-0.1.16.dist-info/WHEEL
nork-0.1.16.dist-info/METADATA
nork-0.1.16.dist-info/RECORD
